{"name":"Chinook","tagline":"Chinook 2 Platform","body":"Chinook 2 est en cours de développement...\r\n\r\n### Généralités.\r\nLe serveur de publication Chinook est une solution complète pour diffuser ses données en  WMS / WFS sécurisé avec une interface d’administration avancée et un client web par défaut. Il permet l’intégration de différentes sources de données (fichiers, bases de données, services externes). Les Services & Composants Chinook font le lien entre les différentes librairies Open Source en validant leur compatibilité et ajoutent des fonctions avancées d’administration, de consultation, édition et gestion des droits…\r\n\r\nComposants client (JavaScript) : interface client / administration\r\n\r\nServices (PHP) : gestion des droits, impressions…\r\n","google":"","note":"Don't delete this file! It's used internally to help with page regeneration."}